data_fabric/__init__.py
data_fabric/components.py
bp_data_fabric-1.0.15.dist-info/LICENSE
bp_data_fabric-1.0.15.dist-info/METADATA
bp_data_fabric-1.0.15.dist-info/WHEEL
bp_data_fabric-1.0.15.dist-info/top_level.txt
bp_data_fabric-1.0.15.dist-info/RECORD
