Metadata-Version: 2.1
Name: bp-data-fabric
Version: 1.0.15
Summary: UNKNOWN
Home-page: UNKNOWN
Author: Bluepineapple
Author-email: avinash@bluepineapple.io
License: UNKNOWN
Platform: UNKNOWN
Requires-Python: >=3.8.10
License-File: LICENSE
Requires-Dist: streamlit (>=1.20.0)
Requires-Dist: bp-query-tool (>=0.0.3)
Requires-Dist: bp-data-grid (>=0.0.9)
Requires-Dist: bp-data-visualization (>=0.0.9)
